pythoven/__init__.py
pythoven-0.1.2.dist-info/METADATA
pythoven-0.1.2.dist-info/WHEEL
pythoven-0.1.2.dist-info/RECORD
