Metadata-Version: 2.1
Name: pythoven
Version: 0.1.2
Summary: 
Author: Piano For AI
Author-email: roszcz@gmail.com
Requires-Python: >=3.9,<4.0
Classifier: Programming Language :: Python :: 3
Classifier: Programming Language :: Python :: 3.9
Classifier: Programming Language :: Python :: 3.10
Classifier: Programming Language :: Python :: 3.11
Requires-Dist: fortepyan (>=0.2.0,<0.3.0)
